{
  "deck": "Day 14 – Spring MVC Fundamentals",
  "mcqs": [
    { "id": 1, "question": "MVC stands for:", "options": ["Model View Controller", "Module View Controller", "Model Version Control", "Main View Controller"], "correct": 0 },
    { "id": 2, "question": "Spring MVC is based on which pattern?", "options": ["Singleton", "Factory", "MVC", "DAO"], "correct": 2 },
    { "id": 3, "question": "DispatcherServlet acts as:", "options": ["View", "Model", "Front Controller", "DAO"], "correct": 2 },
    { "id": 4, "question": "Which annotation marks a controller class?", "options": ["@Service", "@Component", "@Controller", "@Repository"], "correct": 2 },
    { "id": 5, "question": "Which annotation maps URL to controller method?", "options": ["@ComponentScan", "@RequestMapping", "@Autowired", "@Bean"], "correct": 1 },
    { "id": 6, "question": "@GetMapping is a shortcut for:", "options": ["@RequestMapping(method=GET)", "@PostMapping", "@PutMapping", "@DeleteMapping"], "correct": 0 },
    { "id": 7, "question": "@PostMapping is used for:", "options": ["Fetching data", "Submitting data", "Deleting data", "Updating data"], "correct": 1 },
    { "id": 8, "question": "Which object passes data to view?", "options": ["Controller", "Model", "DispatcherServlet", "ViewResolver"], "correct": 1 },
    { "id": 9, "question": "Which annotation reads query parameters?", "options": ["@PathVariable", "@RequestParam", "@RequestBody", "@ResponseBody"], "correct": 1 },
    { "id": 10, "question": "@PathVariable is used to read:", "options": ["Form data", "Query string", "URL path values", "Headers"], "correct": 2 },

    { "id": 11, "question": "Logical view name is resolved by:", "options": ["Controller", "DispatcherServlet", "ViewResolver", "Model"], "correct": 2 },
    { "id": 12, "question": "Which file configures Spring MVC traditionally?", "options": ["web.xml", "pom.xml", "spring-mvc.xml", "hibernate.cfg.xml"], "correct": 2 },
    { "id": 13, "question": "Which layer handles HTTP requests?", "options": ["DAO", "Service", "Controller", "Repository"], "correct": 2 },
    { "id": 14, "question": "Which annotation is used for class-level mapping?", "options": ["@GetMapping", "@PostMapping", "@RequestMapping", "@Autowired"], "correct": 2 },
    { "id": 15, "question": "Which is NOT a Spring MVC component?", "options": ["Controller", "Model", "View", "EntityManager"], "correct": 3 },
    { "id": 16, "question": "DispatcherServlet is configured as:", "options": ["DAO", "Filter", "Servlet", "Listener"], "correct": 2 },
    { "id": 17, "question": "Which supports REST-style URLs?", "options": ["@RequestParam", "@PathVariable", "@Bean", "@Autowired"], "correct": 1 },
    { "id": 18, "question": "Which annotation maps only GET requests?", "options": ["@RequestMapping", "@PostMapping", "@GetMapping", "@Controller"], "correct": 2 },
    { "id": 19, "question": "Which object holds request data for view rendering?", "options": ["ViewResolver", "Model", "DispatcherServlet", "DAO"], "correct": 1 },
    { "id": 20, "question": "Which improves separation of concerns?", "options": ["Scriptlets", "MVC pattern", "Inline JDBC", "Hard coding"], "correct": 1 },

    { "id": 21, "question": "DispatcherServlet delegates request to:", "options": ["DAO", "Service", "Controller", "View"], "correct": 2 },
    { "id": 22, "question": "Which mapping is preferred for readability?", "options": ["@RequestMapping", "@GetMapping / @PostMapping", "XML mapping", "web.xml mapping"], "correct": 1 },
    { "id": 23, "question": "Which annotation binds URL variable to method parameter?", "options": ["@RequestParam", "@PathVariable", "@Autowired", "@Bean"], "correct": 1 },
    { "id": 24, "question": "Which object resolves logical view name to JSP?", "options": ["Controller", "Model", "ViewResolver", "DispatcherServlet"], "correct": 2 },
    { "id": 25, "question": "Which improves maintainability in web apps?", "options": ["Scriptlets", "MVC separation", "Inline SQL", "Hard coding"], "correct": 1 },
    { "id": 26, "question": "Which annotation supports multiple HTTP methods?", "options": ["@GetMapping", "@PostMapping", "@RequestMapping", "@Controller"], "correct": 2 },
    { "id": 27, "question": "Which class handles all incoming requests?", "options": ["Controller", "DispatcherServlet", "ViewResolver", "Model"], "correct": 1 },
    { "id": 28, "question": "Which part prepares model data?", "options": ["View", "Controller", "DispatcherServlet", "JSP"], "correct": 1 },
    { "id": 29, "question": "Which MVC component renders response?", "options": ["Model", "Controller", "View", "DAO"], "correct": 2 },
    { "id": 30, "question": "Which is used to pass multiple attributes to view?", "options": ["Model", "ModelMap", "Both A and B", "DispatcherServlet"], "correct": 2 },

    { "id": 31, "question": "Which config enables controller scanning?", "options": ["@Autowired", "@ComponentScan", "@Bean", "@Scope"], "correct": 1 },
    { "id": 32, "question": "Which annotation reads request parameter optionally?", "options": ["@RequestParam(required=false)", "@PathVariable", "@Bean", "@Autowired"], "correct": 0 },
    { "id": 33, "question": "Which approach avoids servlet code?", "options": ["JSP only", "Spring MVC controllers", "Scriptlets", "Inline JDBC"], "correct": 1 },
    { "id": 34, "question": "Which annotation defines REST-style endpoint (intro)?", "options": ["@Controller", "@RestController", "@Service", "@Repository"], "correct": 1 },
    { "id": 35, "question": "Which improves URL clarity?", "options": ["Query parameters only", "REST-style paths", "Inline SQL", "Scriptlets"], "correct": 1 },
    { "id": 36, "question": "Which MVC part handles navigation logic?", "options": ["View", "Controller", "Model", "DAO"], "correct": 1 },
    { "id": 37, "question": "Which config is required for view resolution?", "options": ["DataSource", "ViewResolver bean", "SessionFactory", "JdbcTemplate"], "correct": 1 },
    { "id": 38, "question": "Which avoids mixing HTML and Java code?", "options": ["Scriptlets", "MVC pattern", "Inline JDBC", "Hard coding"], "correct": 1 },
    { "id": 39, "question": "Which annotation maps POST form submission?", "options": ["@GetMapping", "@PostMapping", "@RequestMapping", "@Controller"], "correct": 1 },
    { "id": 40, "question": "Which component decides next view?", "options": ["Model", "Controller", "DispatcherServlet", "DAO"], "correct": 1 },

    { "id": 41, "question": "Which misuse breaks MVC separation?", "options": ["Controller handling requests", "Business logic in controller", "Using Model", "Using ViewResolver"], "correct": 1 },
    { "id": 42, "question": "Why DispatcherServlet is called front controller?", "options": ["It renders view", "It handles all incoming requests", "It stores data", "It accesses DB"], "correct": 1 },
    { "id": 43, "question": "Which design improves scalability in web apps?", "options": ["Scriptlets", "MVC pattern", "Inline SQL", "Hard coding"], "correct": 1 },
    { "id": 44, "question": "Which approach improves testability of controllers?", "options": ["Inline JDBC", "Thin controllers", "Business logic in JSP", "Hard coding"], "correct": 1 },
    { "id": 45, "question": "Which issue occurs without ViewResolver?", "options": ["Wrong URLs", "Cannot map controllers", "View name resolution fails", "DB error"], "correct": 2 },
    { "id": 46, "question": "Which design keeps controllers lightweight?", "options": ["Business logic in controller", "Delegating to service layer", "Inline SQL", "Scriptlets"], "correct": 1 },
    { "id": 47, "question": "Which approach supports REST transition easily later?", "options": ["Scriptlets", "Spring MVC with annotations", "Inline JDBC", "Hard coding"], "correct": 1 },
    { "id": 48, "question": "Which annotation misuse causes ambiguous mapping?", "options": ["Missing @Controller", "Overlapping @RequestMapping paths", "Missing Model", "Missing ViewResolver"], "correct": 1 },
    { "id": 49, "question": "Which MVC benefit improves maintainability most?", "options": ["Hard coding", "Clear layer separation", "Inline SQL", "Scriptlets"], "correct": 1 },
    { "id": 50, "question": "Which mapping strategy is most readable?", "options": ["Generic @RequestMapping", "HTTP-specific mappings", "XML mappings", "web.xml"], "correct": 1 },

    { "id": 51, "question": "Which annotation reads URL segments safely?", "options": ["@RequestParam", "@PathVariable", "@Autowired", "@Bean"], "correct": 1 },
    { "id": 52, "question": "Which approach avoids servlet boilerplate code?", "options": ["JSP only", "Spring MVC controllers", "Scriptlets", "Inline JDBC"], "correct": 1 },
    { "id": 53, "question": "Which misuse causes tight coupling in web layer?", "options": ["Using Model", "Controller calling DAO directly", "ViewResolver usage", "MVC separation"], "correct": 1 },
    { "id": 54, "question": "Which config ensures JSP view resolution?", "options": ["DataSource bean", "ViewResolver bean", "SessionFactory bean", "JdbcTemplate bean"], "correct": 1 },
    { "id": 55, "question": "Which improves clarity of request handling?", "options": ["One big servlet", "Annotation-based mappings", "Scriptlets", "Hard coding"], "correct": 1 },
    { "id": 56, "question": "Which feature supports clean URL design?", "options": ["Query params only", "@PathVariable", "Inline SQL", "Scriptlets"], "correct": 1 },
    { "id": 57, "question": "Which layer should NOT access DB directly?", "options": ["DAO", "Service", "Controller", "Repository"], "correct": 2 },
    { "id": 58, "question": "Which approach best supports large team development?", "options": ["Scriptlets", "MVC separation", "Inline JDBC", "Hard coding"], "correct": 1 },
    { "id": 59, "question": "Which mistake makes controllers hard to test?", "options": ["Thin controllers", "Business logic inside controllers", "Using Model", "Using ViewResolver"], "correct": 1 },
    { "id": 60, "question": "Which overall approach is best for web layer design?", "options": ["One servlet handling all logic", "Spring MVC with proper layering", "Scriptlets", "Hard coding"], "correct": 1 }
  ]
}
